{
    "apps": [
        {
            "desc": "Code Anaylser is a simple web service which analyses code.",
            "img": "/apps/img/codeanalyser.png",
            "zip": "/apps/zip/C++ CodeAnalyser.zip",
            "git": "http://www.williamsamtaylor.co.uk/programs/cca/index.html"
        },
        {
            "desc": "An Edge of 5 Kingdoms is a small web game made using Phaser",
            "img": "/apps/img/mgd.jpg",
            "zip": "/apps/zip/MobileGameDev.zip",
            "git": "http://www.williamsamtaylor.co.uk/programs/mgd/index.html"
        }
    ]
}